[{"__symbolic":"module","version":3,"metadata":{"FLICKITY_DIRECTIVES":[{"__symbolic":"reference","module":"./components/flickity/flickity.directive","name":"FlickityDirective"},{"__symbolic":"reference","module":"./components/flickity-child/flickity-child.directive","name":"FlickityChildDirective"}]},"exports":[{"from":"./interfaces/flickity-options.interface","export":["FlickityOptions"]},{"from":"./components/flickity/flickity.directive","export":["FlickityDirective"]},{"from":"./components/flickity-child/flickity-child.directive","export":["FlickityChildDirective"]},{"from":"./flickity.module","export":["FlickityModule"]}]},{"__symbolic":"module","version":1,"metadata":{"FLICKITY_DIRECTIVES":[{"__symbolic":"reference","module":"./components/flickity/flickity.directive","name":"FlickityDirective"},{"__symbolic":"reference","module":"./components/flickity-child/flickity-child.directive","name":"FlickityChildDirective"}]},"exports":[{"from":"./interfaces/flickity-options.interface","export":["FlickityOptions"]},{"from":"./components/flickity/flickity.directive","export":["FlickityDirective"]},{"from":"./components/flickity-child/flickity-child.directive","export":["FlickityChildDirective"]},{"from":"./flickity.module","export":["FlickityModule"]}]}]